[
  {
    "ID": "1",
    "Name": "Mahmoud Walid",
    "Date": "2025-05-11",
    "Time": "22:20:37",
    "Status": "Check-in"
  },
  {
    "ID": "2",
    "Name": "Aaron_Peirsol",
    "Date": "2025-05-11",
    "Time": "22:21:26",
    "Status": "Check-in"
  },
  {
    "ID": "2",
    "Name": "Aaron_Peirsol",
    "Date": "2025-05-11",
    "Time": "22:22:03",
    "Status": "Check-out"
  },
  {
    "ID": "1",
    "Name": "Mahmoud Walid",
    "Date": "2025-05-11",
    "Time": "22:22:30",
    "Status": "Check-out"
  },
  {
    "ID": "brad_alexander_smith",
    "Name": "Brad_Alexander_Smith",
    "Date": "2025-05-11",
    "Time": "22:51:27",
    "Status": "Check-in"
  },
  {
    "ID": "brad_alexander_smith",
    "Name": "Brad_Alexander_Smith",
    "Date": "2025-05-11",
    "Time": "22:52:15",
    "Status": "Check-in"
  },
  {
    "ID": "10",
    "Name": "CC",
    "Date": "2025-05-12",
    "Time": "00:13:07",
    "Status": "Check-in"
  },
  {
    "ID": "10",
    "Name": "CC",
    "Date": "2025-05-12",
    "Time": "00:13:29",
    "Status": "Check-in"
  },
  {
    "ID": "maureen_kanka",
    "Name": "Maureen_Kanka",
    "Date": "2025-05-12",
    "Time": "02:43:18",
    "Status": "Check-in"
  },
  {
    "ID": "kemal_dervis",
    "Name": "Kemal_Dervis",
    "Date": "2025-05-12",
    "Time": "03:28:12",
    "Status": "Check-in"
  },
  {
    "ID": "kemal_dervis",
    "Name": "Kemal_Dervis",
    "Date": "2025-05-12",
    "Time": "03:28:26",
    "Status": "Check-in"
  },
  {
    "ID": "maureen_kanka",
    "Name": "Maureen_Kanka",
    "Date": "2025-05-12",
    "Time": "03:28:33",
    "Status": "Check-out"
  },
  {
    "ID": "imad_moustapha",
    "Name": "Imad_Moustapha",
    "Date": "2025-05-12",
    "Time": "03:28:41",
    "Status": "Check-out"
  },
  {
    "ID": "mickey_loomis",
    "Name": "Mickey_Loomis",
    "Date": "2025-05-12",
    "Time": "03:28:53",
    "Status": "Check-out"
  },
  {
    "ID": "imad_moustapha",
    "Name": "Imad_Moustapha",
    "Date": "2025-05-12",
    "Time": "03:29:02",
    "Status": "Check-out"
  },
  {
    "ID": "alexander_payne",
    "Name": "Alexander_Payne",
    "Date": "2025-05-12",
    "Time": "03:30:04",
    "Status": "Check-in"
  },
  {
    "ID": "franz_fischler",
    "Name": "Franz_Fischler",
    "Date": "2025-05-12",
    "Time": "03:32:01",
    "Status": "Check-in"
  },
  {
    "ID": "alexander_payne",
    "Name": "Alexander_Payne",
    "Date": "2025-05-12",
    "Time": "06:11:00",
    "Status": "Check-in"
  },
  {
    "ID": "franz_fischler",
    "Name": "Franz_Fischler",
    "Date": "2025-05-12",
    "Time": "06:11:10",
    "Status": "Check-in"
  },
  {
    "ID": "alexander_payne",
    "Name": "Alexander_Payne",
    "Date": "2025-05-12",
    "Time": "06:11:37",
    "Status": "Check-in"
  },
  {
    "ID": "alexander_payne",
    "Name": "Alexander_Payne",
    "Date": "2025-05-12",
    "Time": "06:14:43",
    "Status": "Check-in"
  }
]